GPUDashboard.py
GPUMonitor.py
runGPUDashboard.py
runGPUMonitor.py
gpu_monitor_isi-0.0.5.dist-info/METADATA
gpu_monitor_isi-0.0.5.dist-info/WHEEL
gpu_monitor_isi-0.0.5.dist-info/entry_points.txt
gpu_monitor_isi-0.0.5.dist-info/top_level.txt
gpu_monitor_isi-0.0.5.dist-info/RECORD
