Metadata-Version: 2.1
Name: gpu-monitor-isi
Version: 0.0.5
Summary: A simple monitor for NVIDIA GPUs
Requires-Dist: requests
Requires-Dist: datetime
Requires-Dist: six
